ingot_redis/__init__.py
ingot_redis/bootstrap/__init__.py
ingot_redis/bootstrap/base.py
ingot_redis/bootstrap/scaffolding/__init__.py
ingot_redis/contrib/__init__.py
ingot_redis/scripts/__init__.py
ingot_redis/scripts/ingot_redis.py
ingot_redis/tests/__init__.py
ingot_redis/tests/functionals/__init__.py
ingot_redis/tests/units/__init__.py
ingot_redis/tests/units/bootstrap/__init__.py
ingot_redis/tests/units/bootstrap/test_base.py
ingot_redis/tests/units/contrib/__init__.py
ingot_redis/tests/units/scripts/__init__.py
ingot_redis/tests/units/scripts/test_ingot_redis.py
ingot_redis-0.1.0.dist-info/LICENSE
ingot_redis-0.1.0.dist-info/METADATA
ingot_redis-0.1.0.dist-info/WHEEL
ingot_redis-0.1.0.dist-info/entry_points.txt
ingot_redis-0.1.0.dist-info/top_level.txt
ingot_redis-0.1.0.dist-info/RECORD
